esr_weather/__init__.py
esr_weather/esr_weather.py
esr_weather-0.0.1.dist-info/LICENSE
esr_weather-0.0.1.dist-info/METADATA
esr_weather-0.0.1.dist-info/WHEEL
esr_weather-0.0.1.dist-info/entry_points.txt
esr_weather-0.0.1.dist-info/top_level.txt
esr_weather-0.0.1.dist-info/RECORD
